noteread/__init__.py
noteread/legado/__init__.py
noteread/legado/shelf/__init__.py
noteread/legado/shelf/base.py
noteread/legado/shelf/libs/__init__.py
noteread/legado/shelf/libs/core.py
noteread/legado/shelf/libs/correct.py
noteread/legado/shelf/libs/mumuceo.py
noteread/legado/shelf/script/__init__.py
noteread/legado/shelf/script/load.py
noteread/rss/__init__.py
noteread/rss/core.py
noteread/rss/element.py
noteread-0.1.12.dist-info/LICENSE
noteread-0.1.12.dist-info/METADATA
noteread-0.1.12.dist-info/WHEEL
noteread-0.1.12.dist-info/top_level.txt
noteread-0.1.12.dist-info/RECORD
