Metadata-Version: 2.1
Name: noteread
Version: 0.1.12
Summary: noteread
Home-page: https://github.com/1007530194
Author: bingtao
Author-email: 1007530194@qq.com
License: UNKNOWN
Platform: UNKNOWN
Requires-Dist: tqdm
